random_stickman.py
stickman.py
abstractart-0.2.0.dist-info/METADATA
abstractart-0.2.0.dist-info/WHEEL
abstractart-0.2.0.dist-info/entry_points.txt
abstractart-0.2.0.dist-info/top_level.txt
abstractart-0.2.0.dist-info/RECORD
