Metadata-Version: 2.4
Name: abstractart
Version: 0.2.0
Summary: Randomly generating abstract stickman
Requires-Python: >=3.12
